helga_roll/__init__.py
helga_roll/plugin.py
helga_roll-1.1.0.dist-info/DESCRIPTION.rst
helga_roll-1.1.0.dist-info/METADATA
helga_roll-1.1.0.dist-info/RECORD
helga_roll-1.1.0.dist-info/WHEEL
helga_roll-1.1.0.dist-info/entry_points.txt
helga_roll-1.1.0.dist-info/metadata.json
helga_roll-1.1.0.dist-info/top_level.txt
helga_roll-1.1.0.dist-info/zip-safe
tests/__init__.py
tests/test_roll.py
